{
  "data": [
    {
      "ticker": "CFLU4",
      "name": "COCA COLA PN",
      "currentPrice": 1000.0,
      "lastQuoteDate": "2003-02-13T00:00:00.000",
      "sector": "",
      "subSector": "",
      "type": "PN",
      "marketCap": 0.0,
      "enterpriseValue": 0.0,
      "pl": 0.0,
      "pvp": 0.0,
      "psr": 0.0,
      "priceToAssets": 0.0,
      "priceToEbit": 0.0,
      "priceToWorkingCapital": 0.0,
      "evToEbit": 0.0,
      "evToEbitda": 0.0,
      "dividendYield": 0.0,
      "roe": 32.15,
      "roic": 17.68,
      "assetTurnover": 1.62,
      "ebitOnAssets": 14.3,
      "grossMargin": 39.3,
      "ebitMargin": 8.88,
      "netMargin": 10.72,
      "lpa": 0.0,
      "vpa": 0.0,
      "assets": 112007000.0,
      "currentAssets": 33438000.0,
      "cash": 5856000.0,
      "grossDebt": 3453000.0,
      "netDebt": -2403000.0,
      "equity": 60351000.0,
      "debtToEquity": -0.04,
      "currentLiquidity": 1.1,
      "revenue": 44806000.0,
      "ebit": 4041000.0,
      "netIncome": 3479000.0,
      "revenueGrowth5y": 8.14
    },
    {
      "ticker": "CLAN3",
      "name": "CLARION ON",
      "currentPrice": 0.0,
      "lastQuoteDate": null,
      "sector": "",
      "subSector": "",
      "type": "ON",
      "marketCap": 0.0,
      "enterpriseValue": 0.0,
      "pl": 0.0,
      "pvp": 0.0,
      "psr": 0.0,
      "priceToAssets": 0.0,
      "priceToEbit": 0.0,
      "priceToWorkingCapital": 0.0,
      "evToEbit": 0.0,
      "evToEbitda": 0.0,
      "dividendYield": 0.0,
      "roe": -1.05,
      "roic": 0.0,
      "assetTurnover": 0.0,
      "ebitOnAssets": 0.0,
      "grossMargin": 0.0,
      "ebitMargin": 0.0,
      "netMargin": 0.0,
      "lpa": 0.0,
      "vpa": 0.0,
      "assets": 1171790000.0,
      "currentAssets": 84641000.0,
      "cash": 8000.0,
      "grossDebt": 85798000.0,
      "netDebt": 85790000.0,
      "equity": 1012240000.0,
      "debtToEquity": 0.08,
      "currentLiquidity": 0.0,
      "revenue": 4309000.0,
      "ebit": 38487000.0,
      "netIncome": 41218000.0,
      "revenueGrowth5y": -63.96
    },
    {
      "ticker": "CSTB3",
      "name": "COMPANHIA SIDERÚRGICA DE TUBARÃO ON",
      "currentPrice": 150.0,
      "lastQuoteDate": "2005-11-07T00:00:00.000",
      "sector": "",
      "subSector": "",
      "type": "ON",
      "marketCap": 0.0,
      "enterpriseValue": 0.0,
      "pl": 0.0,
      "pvp": 0.0,
      "psr": 0.0,
      "priceToAssets": 0.0,
      "priceToEbit": 0.0,
      "priceToWorkingCapital": 0.0,
      "evToEbit": 0.0,
      "evToEbitda": 0.0,
      "dividendYield": 0.0,
      "roe": 20.11,
      "roic": 22.4,
      "assetTurnover": 0.52,
      "ebitOnAssets": 21.1,
      "grossMargin": 45.4,
      "ebitMargin": 40.85,
      "netMargin": 28.98,
      "lpa": 0.0,
      "vpa": 0.0,
      "assets": 11296400000.0,
      "currentAssets": 1937480000.0,
      "cash": 404435000.0,
      "grossDebt": 1162560000.0,
      "netDebt": 758130000.0,
      "equity": 8420670000.0,
      "debtToEquity": 0.09,
      "currentLiquidity": 2.6,
      "revenue": 1047730000.0,
      "ebit": 290700000.0,
      "netIncome": 173262000.0,
      "revenueGrowth5y": 31.91
    },
    {
      "ticker": "CSTB4",
      "name": "COMPANHIA SIDERÚRGICA DE TUBARÃO PN",
      "currentPrice": 147.69,
      "lastQuoteDate": "2005-11-10T00:00:00.000",
      "sector": "",
      "subSector": "",
      "type": "PN",
      "marketCap": 0.0,
      "enterpriseValue": 0.0,
      "pl": 0.0,
      "pvp": 0.0,
      "psr": 0.0,
      "priceToAssets": 0.0,
      "priceToEbit": 0.0,
      "priceToWorkingCapital": 0.0,
      "evToEbit": 0.0,
      "evToEbitda": 0.0,
      "dividendYield": 0.0,
      "roe": 20.11,
      "roic": 22.4,
      "assetTurnover": 0.52,
      "ebitOnAssets": 21.1,
      "grossMargin": 45.4,
      "ebitMargin": 40.85,
      "netMargin": 28.98,
      "lpa": 0.0,
      "vpa": 0.0,
      "assets": 11296400000.0,
      "currentAssets": 1937480000.0,
      "cash": 404435000.0,
      "grossDebt": 1162560000.0,
      "netDebt": 758130000.0,
      "equity": 8420670000.0,
      "debtToEquity": 0.09,
      "currentLiquidity": 2.6,
      "revenue": 1047730000.0,
      "ebit": 290700000.0,
      "netIncome": 173262000.0,
      "revenueGrowth5y": 31.91
    },
    {
      "ticker": "IVTT3",
      "name": "BHG ON NM",
      "currentPrice": 0.0,
      "lastQuoteDate": null,
      "sector": "Exploração de Imóveis",
      "subSector": "Exploração de Imóveis",
      "type": "ON NM",
      "marketCap": 0.0,
      "enterpriseValue": 0.0,
      "pl": 0.0,
      "pvp": 0.0,
      "psr": 0.0,
      "priceToAssets": 0.0,
      "priceToEbit": 0.0,
      "priceToWorkingCapital": 0.0,
      "evToEbit": 0.0,
      "evToEbitda": 0.0,
      "dividendYield": 0.0,
      "roe": -0.4,
      "roic": 0.0,
      "assetTurnover": 0.0,
      "ebitOnAssets": 0.0,
      "grossMargin": 0.0,
      "ebitMargin": 0.0,
      "netMargin": 0.0,
      "lpa": 0.0,
      "vpa": 0.0,
      "assets": 1387870000.0,
      "currentAssets": 166114000.0,
      "cash": 99506000.0,
      "grossDebt": 212154000.0,
      "netDebt": 112648000.0,
      "equity": 1083050000.0,
      "debtToEquity": 0.1,
      "currentLiquidity": 0.0,
      "revenue": 68479000.0,
      "ebit": -2673000.0,
      "netIncome": -10915000.0,
      "revenueGrowth5y": 20.67
    },
    {
      "ticker": "MNSA3",
      "name": "MANASA ON",
      "currentPrice": 0.42,
      "lastQuoteDate": "2006-01-04T00:00:00.000",
      "sector": "",
      "subSector": "",
      "type": "ON",
      "marketCap": 0.0,
      "enterpriseValue": 0.0,
      "pl": 0.0,
      "pvp": 0.0,
      "psr": 0.0,
      "priceToAssets": 0.0,
      "priceToEbit": 0.0,
      "priceToWorkingCapital": 0.0,
      "evToEbit": 0.0,
      "evToEbitda": 0.0,
      "dividendYield": 0.0,
      "roe": 145.7,
      "roic": -13.5,
      "assetTurnover": 0.05,
      "ebitOnAssets": -10.6,
      "grossMargin": 66.8,
      "ebitMargin": -208.15,
      "netMargin": -362.66,
      "lpa": 0.0,
      "vpa": 0.0,
      "assets": 71517000.0,
      "currentAssets": 17142000.0,
      "cash": 12346000.0,
      "grossDebt": 59335000.0,
      "netDebt": 46989000.0,
      "equity": -9105000.0,
      "debtToEquity": -5.16,
      "currentLiquidity": 3.63,
      "revenue": 1185000.0,
      "ebit": -2978000.0,
      "netIncome": -7097000.0,
      "revenueGrowth5y": -41.11
    },
    {
      "ticker": "MNSA4",
      "name": "MANASA PN",
      "currentPrice": 0.47,
      "lastQuoteDate": "2006-03-23T00:00:00.000",
      "sector": "",
      "subSector": "",
      "type": "PN",
      "marketCap": 0.0,
      "enterpriseValue": 0.0,
      "pl": 0.0,
      "pvp": 0.0,
      "psr": 0.0,
      "priceToAssets": 0.0,
      "priceToEbit": 0.0,
      "priceToWorkingCapital": 0.0,
      "evToEbit": 0.0,
      "evToEbitda": 0.0,
      "dividendYield": 0.0,
      "roe": 145.7,
      "roic": -13.5,
      "assetTurnover": 0.05,
      "ebitOnAssets": -10.6,
      "grossMargin": 66.8,
      "ebitMargin": -208.15,
      "netMargin": -362.66,
      "lpa": 0.0,
      "vpa": 0.0,
      "assets": 71517000.0,
      "currentAssets": 17142000.0,
      "cash": 12346000.0,
      "grossDebt": 59335000.0,
      "netDebt": 46989000.0,
      "equity": -9105000.0,
      "debtToEquity": -5.16,
      "currentLiquidity": 3.63,
      "revenue": 1185000.0,
      "ebit": -2978000.0,
      "netIncome": -7097000.0,
      "revenueGrowth5y": -41.11
    },
    {
      "ticker": "PMET3",
      "name": "PRO METALURG ON",
      "currentPrice": 0.0,
      "lastQuoteDate": null,
      "sector": "",
      "subSector": "",
      "type": "ON",
      "marketCap": 0.0,
      "enterpriseValue": 0.0,
      "pl": 0.0,
      "pvp": 0.0,
      "psr": 0.0,
      "priceToAssets": 0.0,
      "priceToEbit": 0.0,
      "priceToWorkingCapital": 0.0,
      "evToEbit": 0.0,
      "evToEbitda": 0.0,
      "dividendYield": 0.0,
      "roe": 4.1,
      "roic": 0.0,
      "assetTurnover": 0.0,
      "ebitOnAssets": 0.0,
      "grossMargin": 0.0,
      "ebitMargin": 0.0,
      "netMargin": 0.0,
      "lpa": 0.0,
      "vpa": 0.0,
      "assets": 1556000.0,
      "currentAssets": 1323000.0,
      "cash": 211000.0,
      "grossDebt": 216672000.0,
      "netDebt": 216461000.0,
      "equity": -290863000.0,
      "debtToEquity": -0.74,
      "currentLiquidity": 0.0,
      "revenue": 7699000.0,
      "ebit": 302000.0,
      "netIncome": -8936000.0,
      "revenueGrowth5y": 37.74
    },
    {
      "ticker": "POPR4",
      "name": "POLIPROPILENO S.A. PN",
      "currentPrice": 10.17,
      "lastQuoteDate": "2005-11-08T00:00:00.000",
      "sector": "",
      "subSector": "",
      "type": "PN",
      "marketCap": 0.0,
      "enterpriseValue": 0.0,
      "pl": 0.0,
      "pvp": 0.0,
      "psr": 0.0,
      "priceToAssets": 0.0,
      "priceToEbit": 0.0,
      "priceToWorkingCapital": 0.0,
      "evToEbit": 0.0,
      "evToEbitda": 0.0,
      "dividendYield": 0.0,
      "roe": 19.93,
      "roic": 15.25,
      "assetTurnover": 1.55,
      "ebitOnAssets": 13.4,
      "grossMargin": 16.4,
      "ebitMargin": 8.66,
      "netMargin": 5.65,
      "lpa": 0.0,
      "vpa": 0.0,
      "assets": 1242060000.0,
      "currentAssets": 464519000.0,
      "cash": 17784000.0,
      "grossDebt": 448872000.0,
      "netDebt": 431088000.0,
      "equity": 545803000.0,
      "debtToEquity": 0.79,
      "currentLiquidity": 1.08,
      "revenue": 521601000.0,
      "ebit": 24027000.0,
      "netIncome": 16842000.0,
      "revenueGrowth5y": 30.93
    },
    {
      "ticker": "PORP4",
      "name": "POLIPROPILENO PARTICIPAÇÕES S.A. PN",
      "currentPrice": 2.4,
      "lastQuoteDate": "2005-11-25T00:00:00.000",
      "sector": "",
      "subSector": "",
      "type": "PN",
      "marketCap": 0.0,
      "enterpriseValue": 0.0,
      "pl": 0.0,
      "pvp": 0.0,
      "psr": 0.0,
      "priceToAssets": 0.0,
      "priceToEbit": 0.0,
      "priceToWorkingCapital": 0.0,
      "evToEbit": 0.0,
      "evToEbitda": 0.0,
      "dividendYield": 0.0,
      "roe": -2.08,
      "roic": 0.0,
      "assetTurnover": 0.0,
      "ebitOnAssets": -0.5,
      "grossMargin": 0.0,
      "ebitMargin": 0.0,
      "netMargin": 0.0,
      "lpa": 0.0,
      "vpa": 0.0,
      "assets": 25341000.0,
      "currentAssets": 514000.0,
      "cash": 189000.0,
      "grossDebt": 0.0,
      "netDebt": -189000.0,
      "equity": 22399000.0,
      "debtToEquity": -0.01,
      "currentLiquidity": 0.0,
      "revenue": 0.0,
      "ebit": -12000.0,
      "netIncome": -46000.0,
      "revenueGrowth5y": 13.66
    }
  ],
  "lastUpdated": "2026-06-17T17:03:26.155915Z",
  "totalAssets": 10,
  "provider": "Fundamentus"
}